tree_sitter_rst-0.2.0.dist-info/LICENSE
tree_sitter_rst-0.2.0.dist-info/WHEEL
tree_sitter_rst-0.2.0.dist-info/METADATA
tree_sitter_rst-0.2.0.dist-info/top_level.txt
tree_sitter_rst-0.2.0.dist-info/RECORD
tree_sitter_rst/__init__.py
tree_sitter_rst/binding.c
tree_sitter_rst/py.typed
tree_sitter_rst/__init__.pyi
tree_sitter_rst/_binding.abi3.so
