Metadata-Version: 2.2
Name: tree-sitter-rst
Version: 0.2.0
Summary: reStructuredText grammar for tree-sitter
Author-email: Santos Gallegos <stsewd@proton.me>
License: MIT
Project-URL: Homepage, https://github.com/stsewd/tree-sitter-rst
Project-URL: Funding, https://github.com/sponsors/stsewd
Keywords: incremental,parsing,tree-sitter,rst
Classifier: Intended Audience :: Developers
Classifier: Topic :: Software Development :: Compilers
Classifier: Topic :: Text Processing :: Linguistic
Classifier: Typing :: Typed
Requires-Python: >=3.10
License-File: LICENSE
Provides-Extra: core
Requires-Dist: tree-sitter~=0.24; extra == "core"
